flet_ivid/__init__.py
flet_ivid/video_container.py
flet_ivid-1.2.dist-info/LICENSE
flet_ivid-1.2.dist-info/METADATA
flet_ivid-1.2.dist-info/WHEEL
flet_ivid-1.2.dist-info/top_level.txt
flet_ivid-1.2.dist-info/RECORD
