Metadata-Version: 2.1
Name: flet-ivid
Version: 1.2
Summary: A package tool that provide basic video player for flet.
Home-page: https://github.com/SKbarbon/flet_ived
Author: SKbarbon
Classifier: Programming Language :: Python :: 3
Classifier: Operating System :: MacOS :: MacOS X
Classifier: Operating System :: Microsoft :: Windows
License-File: LICENSE
Requires-Dist: flet
Requires-Dist: pygame
Requires-Dist: moviepy
Requires-Dist: opencv-python
